AUTHORS
CHANGELOG.txt
DESCRIPTION
LICENSE
MANIFEST.in
README.rst
setup.cfg
setup.py
django_object_faq.egg-info/PKG-INFO
django_object_faq.egg-info/SOURCES.txt
django_object_faq.egg-info/dependency_links.txt
django_object_faq.egg-info/requires.txt
django_object_faq.egg-info/top_level.txt
object_faq/__init__.py
object_faq/admin.py
object_faq/models.py
object_faq/urls.py
object_faq/views.py
object_faq/migrations/0001_initial.py
object_faq/migrations/0002_auto__add_unique_globalobjectdescription_content_type_object_id.py
object_faq/migrations/__init__.py
object_faq/static/.empty
object_faq/static/object_faq/.empty
object_faq/templates/object_faq/.empty
object_faq/templates/object_faq/partials/object_faq.html
object_faq/templatetags/__init__.py
object_faq/templatetags/object_faq_tags.py
object_faq/tests/.object_faq_tags_tests.py.swo
object_faq/tests/__init__.py
object_faq/tests/factories.py
object_faq/tests/models_tests.py
object_faq/tests/object_faq_tags_tests.py
object_faq/tests/runtests.py
object_faq/tests/south_settings.py
object_faq/tests/test_settings.py
object_faq/tests/urls.py
object_faq/tests/test_app/__init__.py
object_faq/tests/test_app/models.py
object_faq/tests/test_app/templates/400.html
object_faq/tests/test_app/templates/500.html