Metadata-Version: 1.0
Name: django-object-faq
Version: 0.1
Summary: A reusable Django app that allows to attach Q&As to any Django model instance
